pytest_otelmark/__init__.py
pytest_otelmark/plugin.py
pytest_otelmark-0.1.0a0.dist-info/WHEEL
pytest_otelmark-0.1.0a0.dist-info/entry_points.txt
pytest_otelmark-0.1.0a0.dist-info/METADATA
pytest_otelmark-0.1.0a0.dist-info/RECORD
